sharktank/__init__.py
sharktank/py.typed
sharktank/build/__init__.py
sharktank/build/actions.py
sharktank/evaluate/perplexity_iree.py
sharktank/evaluate/perplexity_torch.py
sharktank/examples/export_paged_llm_v1.py
sharktank/examples/paged_llm_v1.py
sharktank/examples/validate_paged_llama_model.py
sharktank/examples/pipeline/export_ppffn_net.py
sharktank/examples/sharding/export_ffn_net.py
sharktank/examples/sharding/export_gemm.py
sharktank/examples/sharding/shard_llm_dataset.py
sharktank/export_layer/export_kv_cache.py
sharktank/export_layer/export_moe.py
sharktank/export_layer/export_paged_attention.py
sharktank/kernels/__init__.py
sharktank/kernels/attention.py
sharktank/kernels/base.py
sharktank/kernels/batch_matmul_transpose_b.py
sharktank/kernels/bitcast.py
sharktank/kernels/conv_2d_nchw_fchw.py
sharktank/kernels/einsum_2args_q4.py
sharktank/kernels/gemm_fp4.py
sharktank/kernels/gemm_fp4_asm.py
sharktank/kernels/mlir_kernel.py
sharktank/kernels/mmt_block_scaled_offset_q4.py
sharktank/kernels/mmt_block_scaled_q8.py
sharktank/kernels/mmt_super_block_scaled_offset_q4.py
sharktank/kernels/mmtfp.py
sharktank/kernels/pooling_nchw_sum.py
sharktank/kernels/rotary.py
sharktank/kernels/topk.py
sharktank/kernels/templates/batch_matmul_transpose_b.mlir
sharktank/kernels/templates/conv_2d_nchw_fchw.mlir
sharktank/kernels/templates/einsum_2args_q4.mlir
sharktank/kernels/templates/mmt_block_scaled_offset_q4_unsigned.mlir
sharktank/kernels/templates/mmt_block_scaled_q8_3d.mlir
sharktank/kernels/templates/mmt_super_block_scaled_offset_q4_unsigned_3d.mlir
sharktank/kernels/templates/mmtfp_2d.mlir
sharktank/kernels/templates/mmtfp_3d.mlir
sharktank/kernels/templates/pooling_nchw_sum.mlir
sharktank/kernels/templates/rotary_embedding.mlir
sharktank/kernels/templates/topk_dynamic.mlir
sharktank/kernels/wave/attention.py
sharktank/kernels/wave/extend_attention.py
sharktank/kernels/wave/mxfp4_gemm.py
sharktank/kernels/wave/utils.py
sharktank/layers/__init__.py
sharktank-3.8.0.dist-info/METADATA
sharktank-3.8.0.dist-info/WHEEL
sharktank-3.8.0.dist-info/entry_points.txt
sharktank-3.8.0.dist-info/top_level.txt
sharktank-3.8.0.dist-info/RECORD
