Metadata-Version: 2.4
Name: sharktank
Version: 3.8.0
Summary: SHARK layers and inference models for genai
Author: SHARK Authors
License-Expression: Apache-2.0
Project-URL: Repository, https://github.com/nod-ai/shark-ai
Classifier: Development Status :: 3 - Alpha
Classifier: Programming Language :: Python :: 3
Requires-Dist: iree-turbine
Requires-Dist: fire>=0.7
Requires-Dist: gguf>=0.11.0
Requires-Dist: numpy
Requires-Dist: huggingface-hub
Requires-Dist: transformers==4.52.1
Requires-Dist: datasets
Requires-Dist: einops
Requires-Dist: sentencepiece
Requires-Dist: fastapi>=0.112.2
Requires-Dist: uvicorn>=0.30.6
Provides-Extra: dev
Requires-Dist: azure-identity>=1.19; extra == "dev"
Requires-Dist: azure-storage-blob>=12.24; extra == "dev"
Provides-Extra: testing
Requires-Dist: accelerate; extra == "testing"
Requires-Dist: datasets==3.0.0; extra == "testing"
Requires-Dist: diffusers; extra == "testing"
Requires-Dist: parameterized; extra == "testing"
Requires-Dist: protobuf; extra == "testing"
Requires-Dist: pytest==8.0.0; extra == "testing"
Requires-Dist: pytest-html; extra == "testing"
Requires-Dist: pytest-cov; extra == "testing"
Requires-Dist: pytest-timeout; extra == "testing"
Requires-Dist: pytest-xdist==3.5.0; extra == "testing"
Requires-Dist: safetensors>=0.4.5; extra == "testing"
